{
    "mohitrawat17906@gmail.com": {
        "username": "mohit",
        "password": "kda"
    },
    "mohitrawat17903@gmail.com": {
        "username": "Rawa",
        "password": "kdakk"
    },
    "faa@gmail": {
        "username": "hola",
        "password": "faha"
    },
    "faa@gmail.com": {
        "username": "hola",
        "password": "faha"
    },
    "fsaa@gmail.com": {
        "username": "hola",
        "password": "faha"
    },
    "fsaaff@gmail.com": {
        "username": "hola",
        "password": "faha"
    },
    "fsahaff@gmail.com": {
        "username": "hola",
        "password": "faha"
    },
    "somitahg@132.com": {
        "username": "mohit",
        "password": "uyhgfc"
    }
}